setup.py
muto/__init__.py
muto/client.py
muto/image.py
muto/processor.py
muto/server.py
muto.egg-info/PKG-INFO
muto.egg-info/SOURCES.txt
muto.egg-info/dependency_links.txt
muto.egg-info/not-zip-safe
muto.egg-info/top_level.txt