Metadata-Version: 1.0
Name: muto
Version: 0.1.1
Summary: Server and corresponding client library for ImageMagick-based image manipulation and conversion
Home-page: http://github.com/philippbosch/muto
Author: Philipp Bosch
Author-email: hello@pb.io
License: UNKNOWN
Platform: UNKNOWN
Classifier: Development Status :: 4 - Beta
Classifier: Environment :: Web Environment
Classifier: Intended Audience :: Developers
Classifier: License :: OSI Approved :: MIT License
Classifier: Operating System :: OS Independent
Classifier: Programming Language :: Python
